{
  "ok": true,
  "state": "熊市反弹",
  "trend": "趋势空",
  "funding": "资金进攻",
  "risk_level": "MEDIUM",
  "confidence": 0.4591288883122325,
  "validation": {
    "risk_thermometer": "高烧威胁",
    "ath_drawdown": 37.38396918494635,
    "ath_price": 106194.85,
    "etf_accelerator": "逆风",
    "etf_net_flow": 0.0,
    "etf_aum": 90132428064.0,
    "etf_flow_14d_sum": -3123300000.0,
    "etf_flow_pos_ratio": 0.23333333333333334,
    "etf_flow_recent_avg": -92142857.14285715,
    "etf_flow_prev_avg": -354042857.14285713,
    "etf_flow_trend": "up",
    "etf_aum_trend": "down"
  },
  "metadata": {
    "btc_price": 66495.0,
    "ma50": 73732.09599999999,
    "ma200": 77565.10595,
    "ma50_slope": -0.3590530369526612,
    "ma200_slope": -0.15386794367354684,
    "total_market_cap": 2366109611169.8105,
    "stablecoin_market_cap": 267789450729.41754,
    "stablecoin_ratio": 11.3177111265366,
    "stablecoin_change": -10480980172.997559,
    "stablecoin_ratio_change": 3.317711126536601,
    "stablecoin_ratio_gap": null,
    "stablecoin_slope": 0.7893530813888328,
    "total_slope": 0.7893530813888106,
    "ath_drawdown": 37.38396918494635
  }
}