{
  "ok": true,
  "state": "熊市反弹",
  "trend": "趋势空",
  "funding": "资金进攻",
  "risk_level": "MEDIUM",
  "confidence": 0.6316646445482256,
  "validation": {
    "risk_thermometer": "高烧威胁",
    "ath_drawdown": 38.42843138496125,
    "ath_price": 124797.86,
    "etf_accelerator": "钝化",
    "etf_net_flow": 0.0,
    "etf_aum": 83830573952.0,
    "etf_flow_14d_sum": 1188000000.0,
    "etf_flow_pos_ratio": 0.6,
    "etf_flow_recent_avg": 135342857.14285713,
    "etf_flow_prev_avg": 34371428.571428575,
    "etf_flow_trend": "up",
    "etf_aum_trend": "up"
  },
  "metadata": {
    "btc_price": 76840.0,
    "ma50": 70028.6348,
    "ma200": 87020.84664999999,
    "ma50_slope": 0.19905872313059625,
    "ma200_slope": -0.21496328013376198,
    "total_market_cap": 2683914370707.09,
    "stablecoin_market_cap": 271253410715.29095,
    "stablecoin_ratio": 10.10663431277161,
    "stablecoin_change": 17875915815.517517,
    "stablecoin_ratio_change": 2.106634312771609,
    "stablecoin_ratio_gap": null,
    "stablecoin_slope": 0.7509255173825613,
    "total_slope": 0.7509255173825391,
    "ath_drawdown": 38.42843138496125
  }
}