{
  "ok": true,
  "state": "熊市消化",
  "trend": "趋势空",
  "funding": "资金防守",
  "risk_level": "LOW",
  "confidence": 0.43503435748311486,
  "validation": {
    "risk_thermometer": "高烧威胁",
    "ath_drawdown": 42.347814702350846,
    "ath_price": 110675.77,
    "etf_accelerator": "逆风",
    "etf_net_flow": 0.0,
    "etf_aum": 90132428064.0,
    "etf_flow_14d_sum": -3745300000.0,
    "etf_flow_pos_ratio": 0.26666666666666666,
    "etf_flow_recent_avg": -263900000.0,
    "etf_flow_prev_avg": -271142857.14285713,
    "etf_flow_trend": "up",
    "etf_aum_trend": "down"
  },
  "metadata": {
    "btc_price": 63807.0,
    "ma50": 75652.315,
    "ma200": 78407.53349999999,
    "ma50_slope": -0.2563395897510312,
    "ma200_slope": -0.18707321287049217,
    "total_market_cap": 2281812802783.7754,
    "stablecoin_market_cap": 268827436460.00424,
    "stablecoin_ratio": 11.78130984855721,
    "stablecoin_change": -18417689318.523224,
    "stablecoin_ratio_change": 3.7813098485572105,
    "stablecoin_ratio_gap": null,
    "stablecoin_slope": -2.061019096444694,
    "total_slope": -2.0610190964446717,
    "ath_drawdown": 42.347814702350846
  }
}