{
  "ok": true,
  "state": "熊市消化",
  "trend": "趋势空",
  "funding": "资金防守",
  "risk_level": "LOW",
  "confidence": 0.5947464987493886,
  "validation": {
    "risk_thermometer": "高烧威胁",
    "ath_drawdown": 37.20725659879104,
    "ath_price": 124797.86,
    "etf_accelerator": "顺风",
    "etf_net_flow": 345400000.0,
    "etf_aum": 83830573952.0,
    "etf_flow_14d_sum": 1989600000.0,
    "etf_flow_pos_ratio": 0.6333333333333333,
    "etf_flow_recent_avg": 16585714.285714285,
    "etf_flow_prev_avg": 267642857.14285713,
    "etf_flow_trend": "down",
    "etf_aum_trend": "up"
  },
  "metadata": {
    "btc_price": 78364.0,
    "ma50": 72506.9622,
    "ma200": 83894.8934,
    "ma50_slope": 0.23356018650737553,
    "ma200_slope": -0.23589518069244697,
    "total_market_cap": 2678840296811.6387,
    "stablecoin_market_cap": 273469524664.74365,
    "stablecoin_ratio": 10.208504216926544,
    "stablecoin_change": 35488528488.65521,
    "stablecoin_ratio_change": 2.208504216926544,
    "stablecoin_ratio_gap": null,
    "stablecoin_slope": -0.08116847734245258,
    "total_slope": -0.08116847734247479,
    "ath_drawdown": 37.20725659879104
  }
}